plugwise/__init__.py
plugwise/common.py
plugwise/constants.py
plugwise/data.py
plugwise/exceptions.py
plugwise/helper.py
plugwise/py.typed
plugwise/smile.py
plugwise/smilecomm.py
plugwise/util.py
plugwise/legacy/data.py
plugwise/legacy/helper.py
plugwise/legacy/smile.py
plugwise-1.11.2.dist-info/licenses/LICENSE
plugwise-1.11.2.dist-info/METADATA
plugwise-1.11.2.dist-info/WHEEL
plugwise-1.11.2.dist-info/top_level.txt
plugwise-1.11.2.dist-info/RECORD
