Metadata-Version: 2.4
Name: plugwise
Version: 1.11.2
Summary: Plugwise Smile (Adam/Anna/P1) and Stretch module for Python 3.
Author: Plugwise device owners
Maintainer: bouwew, CoMPaTech
License-Expression: MIT
Project-URL: Source Code, https://github.com/plugwise/python-plugwise
Project-URL: Bug Reports, https://github.com/plugwise/python-plugwise/issues
Keywords: home,automation,plugwise,module
Classifier: Development Status :: 5 - Production/Stable
Classifier: Intended Audience :: Developers
Classifier: Operating System :: OS Independent
Classifier: Programming Language :: Python :: 3.14
Classifier: Programming Language :: Python :: 3.13
Classifier: Topic :: Home Automation
Requires-Python: >=3.13
License-File: LICENSE
Requires-Dist: aiofiles
Requires-Dist: aiohttp
Requires-Dist: defusedxml
Requires-Dist: munch
Requires-Dist: python-dateutil
Dynamic: license-file
